hamsclient/__init__.py
hamsclient/__main__.py
hamsclient/client.py
hamsclient-0.2.3.dist-info/LICENSE
hamsclient-0.2.3.dist-info/METADATA
hamsclient-0.2.3.dist-info/WHEEL
hamsclient-0.2.3.dist-info/top_level.txt
hamsclient-0.2.3.dist-info/RECORD
