Metadata-Version: 2.1
Name: hamsclient
Version: 0.2.3
Summary: Library to get data from meteo swiss
Home-page: https://github.com/websylv/meteoswiss
Author: websylv
Author-email: div@webhu.org
License: MIT
Platform: UNKNOWN
Classifier: Development Status :: 2 - Pre-Alpha
Classifier: License :: OSI Approved :: MIT License
Classifier: Programming Language :: Python :: 3.6
Classifier: Programming Language :: Python :: 3.7
License-File: LICENSE
Requires-Dist: requests (>=2.22.0)
Requires-Dist: pandas (>=0.25.3)
Requires-Dist: beautifulsoup4 (>=4.8.2geopy>=2.0.0)
